rka/__init__.py
rka/cli.py
rka/model.py
rka/redis_key_analyzer.py
rka/report.py
rka/scan.py
redis_key_analyzer-0.1.6.dist-info/LICENSE
redis_key_analyzer-0.1.6.dist-info/METADATA
redis_key_analyzer-0.1.6.dist-info/WHEEL
redis_key_analyzer-0.1.6.dist-info/entry_points.txt
redis_key_analyzer-0.1.6.dist-info/top_level.txt
redis_key_analyzer-0.1.6.dist-info/RECORD
