Metadata-Version: 2.1
Name: redis-key-analyzer
Version: 0.1.6
Summary: Redis Key Analyzer is a CLI tool for scanning and analyzing Redis database keys, providing insights into their distribution, type, memory usage, and TTL.
Author: Ryan Kang
Author-email: serious8builder@gmail.com
Project-URL: Source, https://github.com/runnable38/redis-key-analyzer
Keywords: redis,pypi,redis keys analyzer
Classifier: Development Status :: 3 - Alpha
Classifier: Intended Audience :: Developers
Classifier: Environment :: Console
Classifier: Topic :: Utilities
Classifier: Programming Language :: Python :: 3.9
Requires-Python: >=3.9
License-File: LICENSE
Requires-Dist: click
Requires-Dist: redis
Requires-Dist: tqdm
Requires-Dist: prettytable
